sptz.py
sputchedtools.py
sputchedtools-0.38.15.dist-info/METADATA
sputchedtools-0.38.15.dist-info/WHEEL
sputchedtools-0.38.15.dist-info/top_level.txt
sputchedtools-0.38.15.dist-info/RECORD
