Metadata-Version: 2.4
Name: sputchedtools
Version: 0.38.15
Author-email: Sputchik <sputchik@gmail.com>
License-Expression: MIT
Project-URL: Repository, https://github.com/Sputchik/sputchedtools
Project-URL: Issues, https://github.com/Sputchik/sputchedtools/issues
Classifier: Development Status :: 4 - Beta
Classifier: Programming Language :: Python :: 3.10
Classifier: Programming Language :: Python :: 3.11
Classifier: Programming Language :: Python :: 3.12
Classifier: Programming Language :: Python :: 3.13
Requires-Python: >=3.10
